QUICKFAST/__init__.py
QUICKFAST/CSV/mat_data.csv
QUICKFAST/CSV/sales_data.csv
QUICKFAST/DBCOMMANDS/Staging.txt
QUICKFAST/DBCOMMANDS/database.txt
QUICKFAST/EXCEL/pivat table.xlsx
QUICKFAST/EXCEL/what if 1.xlsx
QUICKFAST/PYTHON/Data_Visualization.py
QUICKFAST/PYTHON/Pandas_Searborn_Insight_Generate.py
QUICKFAST/R/Data_Classification.R
QUICKFAST/R/Data_Clustering.R
QUICKFAST/R/Linear_Regression.R
QUICKFAST/TEXT/BI PRACTICALS.txt
quickfast-0.6.dist-info/METADATA
quickfast-0.6.dist-info/WHEEL
quickfast-0.6.dist-info/top_level.txt
quickfast-0.6.dist-info/RECORD
